<PAMDataset>
  <SRS dataAxisToSRSAxisMapping="1,2">PROJCS["HTRS96 / Croatia TM",GEOGCS["HTRS96",DATUM["Croatian_Terrestrial_Reference_System",SPHEROID["GRS 1980",6378137,298.257222101,AUTHORITY["EPSG","7019"]],AUTHORITY["EPSG","6761"]],PRIMEM["Greenwich",0,AUTHORITY["EPSG","8901"]],UNIT["degree",0.0174532925199433,AUTHORITY["EPSG","9122"]],AUTHORITY["EPSG","4761"]],PROJECTION["Transverse_Mercator"],PARAMETER["latitude_of_origin",0],PARAMETER["central_meridian",16.5],PARAMETER["scale_factor",0.9999],PARAMETER["false_easting",500000],PARAMETER["false_northing",0],UNIT["metre",1,AUTHORITY["EPSG","9001"]],AXIS["Easting",EAST],AXIS["Northing",NORTH],AUTHORITY["EPSG","3765"]]</SRS>
  <GeoTransform>  5.5681387970000005e+05,  4.9994871975983468e-01,  0.0000000000000000e+00,  4.8130443128000004e+06,  0.0000000000000000e+00, -4.9997660024164714e-01</GeoTransform>
  <Metadata domain="IMAGE_STRUCTURE">
    <MDI key="INTERLEAVE">PIXEL</MDI>
  </Metadata>
  <Metadata>
    <MDI key="AREA_OR_POINT">Area</MDI>
  </Metadata>
  <PAMRasterBand band="1">
    <NoDataValue>0.00000000000000E+00</NoDataValue>
  </PAMRasterBand>
  <PAMRasterBand band="2">
    <NoDataValue>0.00000000000000E+00</NoDataValue>
  </PAMRasterBand>
  <PAMRasterBand band="3">
    <NoDataValue>0.00000000000000E+00</NoDataValue>
  </PAMRasterBand>
  <PAMRasterBand band="4">
    <NoDataValue>0.00000000000000E+00</NoDataValue>
  </PAMRasterBand>
</PAMDataset>
